pytest_statsd/__init__.py
pytest_statsd/plugin.py
pytest_statsd-1.1.6.dist-info/LICENSE.md
pytest_statsd-1.1.6.dist-info/METADATA
pytest_statsd-1.1.6.dist-info/WHEEL
pytest_statsd-1.1.6.dist-info/entry_points.txt
pytest_statsd-1.1.6.dist-info/top_level.txt
pytest_statsd-1.1.6.dist-info/RECORD
