Metadata-Version: 2.1
Name: pytest-statsd
Version: 1.1.6
Summary: pytest plugin for reporting to graphite
Home-page: https://github.com/jlane9/pytest-statsd
Author: jlane
Author-email: jlane@fanthreesixty.com
License: MIT
Project-URL: Documentation, https://pytest-statsd.readthedocs.io/en/latest/
Project-URL: Tracker, https://github.com/jlane9/pytest-statsd/issues
Keywords: py.test pytest statsd graphite grafana report
Platform: UNKNOWN
Classifier: Development Status :: 5 - Production/Stable
Classifier: Framework :: Pytest
Classifier: Intended Audience :: Developers
Classifier: License :: OSI Approved :: MIT License
Classifier: Natural Language :: English
Classifier: Operating System :: POSIX
Classifier: Operating System :: Microsoft :: Windows
Classifier: Operating System :: MacOS :: MacOS X
Classifier: Programming Language :: Python :: 2.7
Classifier: Topic :: Software Development :: Testing
Classifier: Topic :: Software Development :: Quality Assurance
Classifier: Topic :: Software Development :: Libraries
Classifier: Topic :: Utilities
Requires-Python: >=2.7
Requires-Dist: pytest (>=3.0.0)
Requires-Dist: statsd (>=3.2.1)
Provides-Extra: release
Requires-Dist: bumpversion (>=0.5.0) ; extra == 'release'
Requires-Dist: Sphinx (>=1.8.0) ; extra == 'release'
Requires-Dist: sphinx-autobuild (>=0.7.0) ; extra == 'release'
Requires-Dist: sphinx-rtd-theme (>=0.4.2) ; extra == 'release'
Requires-Dist: twine (>=1.12.0) ; extra == 'release'
